tkterminal/__init__.py
tkterminal/ternimal.py
tkterminal/text.py
tkterminal/utils.py
tkterminal-0.1.0.dist-info/LICENSE
tkterminal-0.1.0.dist-info/METADATA
tkterminal-0.1.0.dist-info/WHEEL
tkterminal-0.1.0.dist-info/top_level.txt
tkterminal-0.1.0.dist-info/RECORD
