Metadata-Version: 2.1
Name: tkterminal
Version: 0.1.0
Summary: Terminal widget for Tkinter library.
Home-page: https://github.com/Saadmairaj/tkterminal
Author: Saad Mairaj
Author-email: Saadmairaj@yahoo.in
License: Apache
Project-URL: Documentation, https://github.com/Saadmairaj/tkterminal#documentation
Project-URL: Bug Report, https://github.com/Saadmairaj/tkterminal/issues
Keywords: tkinter,terminal,subprocess,tkinter-widget,shell,bash/sh,bash
Platform: UNKNOWN
Classifier: Development Status :: 5 - Production/Stable
Classifier: Intended Audience :: Developers
Classifier: Intended Audience :: Education
Classifier: Intended Audience :: End Users/Desktop
Classifier: License :: OSI Approved :: Apache Software License
Classifier: Topic :: Software Development :: Libraries :: Python Modules
